dffml_service_http/__init__.py
dffml_service_http/api.js
dffml_service_http/cli.py
dffml_service_http/routes.py
dffml_service_http/version.py
dffml_service_http/util/__init__.py
dffml_service_http/util/testing.py
tests/__init__.py
tests/dataflow.py
tests/test_cli.py
tests/test_routes.py
tests/test_rproxy.py
dffml_service_http-0.1.0.post0.dist-info/LICENSE
dffml_service_http-0.1.0.post0.dist-info/METADATA
dffml_service_http-0.1.0.post0.dist-info/WHEEL
dffml_service_http-0.1.0.post0.dist-info/entry_points.txt
dffml_service_http-0.1.0.post0.dist-info/top_level.txt
dffml_service_http-0.1.0.post0.dist-info/RECORD
